manimvtk/__init__.py
manimvtk/__main__.py
manimvtk/constants.py
manimvtk/data_structures.py
manimvtk/typing.py
manimvtk/_config/__init__.py
manimvtk/_config/cli_colors.py
manimvtk/_config/default.cfg
manimvtk/_config/logger_utils.py
manimvtk/_config/utils.py
manimvtk/animation/__init__.py
manimvtk/animation/animation.py
manimvtk/animation/changing.py
manimvtk/animation/composition.py
manimvtk/animation/creation.py
manimvtk/animation/fading.py
manimvtk/animation/growing.py
manimvtk/animation/indication.py
manimvtk/animation/movement.py
manimvtk/animation/numbers.py
manimvtk/animation/rotation.py
manimvtk/animation/specialized.py
manimvtk/animation/speedmodifier.py
manimvtk/animation/transform.py
manimvtk/animation/transform_matching_parts.py
manimvtk/animation/updaters/__init__.py
manimvtk/animation/updaters/mobject_update_utils.py
manimvtk/animation/updaters/update.py
manimvtk/camera/__init__.py
manimvtk/camera/camera.py
manimvtk/camera/mapping_camera.py
manimvtk/camera/moving_camera.py
manimvtk/camera/multi_camera.py
manimvtk/camera/three_d_camera.py
manimvtk/cli/__init__.py
manimvtk/cli/default_group.py
manimvtk/cli/cfg/__init__.py
manimvtk/cli/cfg/group.py
manimvtk/cli/checkhealth/__init__.py
manimvtk/cli/checkhealth/checks.py
manimvtk/cli/checkhealth/commands.py
manimvtk/cli/init/__init__.py
manimvtk/cli/init/commands.py
manimvtk/cli/plugins/__init__.py
manimvtk/cli/plugins/commands.py
manimvtk/cli/render/__init__.py
manimvtk/cli/render/commands.py
manimvtk/cli/render/ease_of_access_options.py
manimvtk/cli/render/global_options.py
manimvtk/cli/render/output_options.py
manimvtk/cli/render/render_options.py
manimvtk/mobject/__init__.py
manimvtk/mobject/frame.py
manimvtk/mobject/graph.py
manimvtk/mobject/logo.py
manimvtk/mobject/matrix.py
manimvtk/mobject/mobject.py
manimvtk/mobject/table.py
manimvtk/mobject/utils.py
manimvtk/mobject/value_tracker.py
manimvtk/mobject/vector_field.py
manimvtk/mobject/geometry/__init__.py
manimvtk/mobject/geometry/arc.py
manimvtk-0.19.0.post6.dist-info/METADATA
manimvtk-0.19.0.post6.dist-info/WHEEL
manimvtk-0.19.0.post6.dist-info/entry_points.txt
manimvtk-0.19.0.post6.dist-info/licenses/LICENSE
manimvtk-0.19.0.post6.dist-info/licenses/LICENSE.community
manimvtk-0.19.0.post6.dist-info/licenses/LICENSE.manimvtk
manimvtk-0.19.0.post6.dist-info/RECORD
