Metadata-Version: 2.4
Name: manimvtk
Version: 0.19.0.post6
Summary: Animation engine for explanatory math videos with VTK scientific visualization support.
Project-URL: repository, https://github.com/mathifylabs/manimVTK
Project-URL: documentation, https://manimvtk.mathify.dev
Project-URL: homepage, https://manimvtk.mathify.dev
Project-URL: Bug Tracker, https://github.com/mathifylabs/manimVTK/issues
Project-URL: X / Twitter, https://x.com/mathify_dev
Author-email: "José Alvarez (Mathify.dev)" <jose@mathify.dev>, The Manim Community Developers <contact@manim.community>, Grant '3Blue1Brown' Sanderson <grant@3blue1brown.com>
License-Expression: MIT
License-File: LICENSE
License-File: LICENSE.community
License-File: LICENSE.manimvtk
Classifier: Development Status :: 4 - Beta
Classifier: License :: OSI Approved :: MIT License
Classifier: Natural Language :: English
Classifier: Programming Language :: Python :: 3.9
Classifier: Programming Language :: Python :: 3.10
Classifier: Programming Language :: Python :: 3.11
Classifier: Programming Language :: Python :: 3.12
Classifier: Programming Language :: Python :: 3.13
Classifier: Topic :: Multimedia :: Graphics
Classifier: Topic :: Multimedia :: Video
Classifier: Topic :: Scientific/Engineering
Classifier: Topic :: Scientific/Engineering :: Visualization
Requires-Python: >=3.9
Requires-Dist: audioop-lts>=0.2.1; python_full_version >= '3.13'
Requires-Dist: av<14.0.0,>=9.0.0
Requires-Dist: beautifulsoup4>=4.12
Requires-Dist: click>=8.0
Requires-Dist: cloup>=2.0.0
Requires-Dist: decorator>=4.3.2
Requires-Dist: importlib-metadata>=8.6.1; python_full_version < '3.10'
Requires-Dist: isosurfaces>=0.1.0
Requires-Dist: manimpango<1.0.0,>=0.5.0
Requires-Dist: mapbox-earcut>=1.0.0
Requires-Dist: moderngl-window>=2.0.0
Requires-Dist: moderngl<6.0.0,>=5.0.0
Requires-Dist: networkx>=2.6
Requires-Dist: numpy>=2.0
Requires-Dist: numpy>=2.1; python_full_version >= '3.10'
Requires-Dist: pillow>=9.1
Requires-Dist: pycairo<2.0.0,>=1.13
Requires-Dist: pydub>=0.20.0
Requires-Dist: pygments>=2.0.0
Requires-Dist: rich>=12.0.0
Requires-Dist: scipy>=1.13.0
Requires-Dist: scipy>=1.14.0; python_full_version >= '3.13'
Requires-Dist: screeninfo>=0.7
Requires-Dist: skia-pathops>=0.7.0
Requires-Dist: srt>=3.0.0
Requires-Dist: svgelements>=1.8.0
Requires-Dist: tqdm>=4.0.0
Requires-Dist: typing-extensions>=4.12.0
Requires-Dist: watchdog>=2.0.0
Provides-Extra: gui
Requires-Dist: dearpygui>=1.0.0; extra == 'gui'
Provides-Extra: jupyterlab
Requires-Dist: jupyterlab>=4.3.4; extra == 'jupyterlab'
Requires-Dist: notebook>=7.3.2; extra == 'jupyterlab'
Provides-Extra: scientific
Requires-Dist: pyvista>=0.40.0; extra == 'scientific'
Requires-Dist: vtk>=9.0.0; extra == 'scientific'
Provides-Extra: vtk
Requires-Dist: vtk>=9.0.0; extra == 'vtk'
